pycounts_mdah/__init__.py
pycounts_mdah/plotting.py
pycounts_mdah/pycounts_mdah.py
pycounts_mdah-0.1.0.dist-info/LICENSE
pycounts_mdah-0.1.0.dist-info/METADATA
pycounts_mdah-0.1.0.dist-info/WHEEL
pycounts_mdah-0.1.0.dist-info/RECORD
